Workbook

Sheet Допущения
A1: ДОПУЩЕНИЯ МОДЕЛИ — меняй жёлтые ячейки, всё остальное пересчитается само
A3: Параметр | B3: Значение | C3: Ед. | D3: Комментарий
A4: База по выручке (среднее июнь-июль) | B4: 2403436 | C4: ₽/мес | D4: Единственные два «чистых» закрытых месяца — так ты сама пометила в П&Л
A5: Рост/спад к базе — Базовый сценарий | B5: 0 | C5: % | D5: 0% = держим уровень июня-июля
A6: Рост/спад к базе — Оптимистичный сценарий | B6: 0.1 | C6: %
A7: Рост/спад к базе — Пессимистичный сценарий | B7: -0.15 | C7: % | D7: Август пока слабее базы — см. лист «Драйверы YClients»
A8: Переменные расходы, % от выручки | B8: 0.493 | C8: % | D8: Среднее «Прямые расходы» / Выручка за июнь-июль из твоего П&Л (материалы + ЗП мастеров)
A9: Постоянные расходы | B9: 724000 | C9: ₽/мес | D9: «Косвенные расходы» июнь-июль БЕЗ закупки космметики (аренда, ФОТ офиса, IT, банк/налоги)
A10: Закупка косметики на продажу (сглажено) | B10: 134438 | C10: ₽/мес | D10: (Сумма закупок янв-авг) / 8 — временное решение, см. лист «Косметика — методология»

Sheet П&Л факт 2026
A1: П&Л факт — из выгрузки Adesk (2026-08-21), без изменений
A2: Статья | B2: Январь | C2: Февраль | D2: Март | E2: Апрель | F2: Май | G2: Июнь | H2: Июль | I2: Август*
A3: Выручка | B3: 607057 | C3: 711918 | D3: 1949364 | E3: 1451132 | F3: 2657327 | G3: 2417021 | H3: 2389851 | I3: 1130940
A4: Прямые расходы (переменные) | B4: -422251 | C4: -425170 | D4: -1120269 | E4: -739891 | F4: -1556820 | G4: -1096289 | H4: -1274531 | I4: -133291
A5: в т.ч. Расходные материалы | B5: -84976 | C5: -117700 | D5: -729571 | E5: -333935 | F5: -920919 | G5: -551863 | H5: -581642 | I5: -108291
A6: в т.ч. ФОТ специалистов | B6: -337275 | C6: -307470 | D6: -390698 | E6: -405956 | F6: -635901 | G6: -544426 | H6: -692889 | I6: -25000
A7: Валовая прибыль | B7: 184806 | C7: 286748 | D7: 829095 | E7: 711241 | F7: 1100507 | G7: 1320732 | H7: 1115320 | I7: 997649
A8: Косвенные расходы (постоянные+прочее) | B8: -282741 | C8: -444671 | D8: -942541 | E8: -621197 | F8: -691519 | G8: -1258711 | H8: -883135 | I8: -523122
A9: в т.ч. Закупка косметики на продажу | B9: 0 | C9: 0 | D9: -298880 | E9: 0 | F9: -38430 | G9: -503954 | H9: -189243 | I9: -45000
A10: Операционная прибыль | B10: -97935 | C10: -157923 | D10: -113446 | E10: 90044 | F10: 408989 | G10: 62021 | H10: 232184 | I10: 474527
A11: Чистая прибыль | B11: -104220 | C11: -158413 | D11: -117900 | E11: 100219 | F11: 408989 | G11: -3026 | H11: 229184 | I11: 444092
A12: * Август — не закрытый месяц (данные по 21.08), не показатель за полный месяц.

Sheet Драйверы YClients
A1: Операционные драйверы — из YClients-пайплайна дашборда (не из Adesk)
A2: Метрика | B2: Январь | C2: Февраль | D2: Март | E2: Апрель | F2: Май | G2: Июнь | H2: Июль | I2: Август*
A3: Выручка (касса, YClients) | B3: 1435736 | C3: 1581992 | D3: 1948045 | E3: 1909183 | F3: 2829133 | G3: 2341497 | H3: 2259505 | I3: 1130740
A4: Визиты | B4: 219 | C4: 255 | D4: 330 | E4: 304 | F4: 358 | G4: 372 | H4: 273 | I4: 181
A5: Средний чек, ₽ | B5: 6556 | C5: 6204 | D5: 5903 | E5: 6280 | F5: 7903 | G5: 6294 | H5: 8277 | I5: 6247
A6: Новые клиенты | B6: 27 | C6: 50 | D6: 55 | E6: 54 | F6: 46 | G6: 55 | H6: 44 | I6: 27
A7: Повторные клиенты | B7: 127 | C7: 124 | D7: 165 | E7: 154 | F7: 181 | G7: 161 | H7: 136 | I7: 112
A8: Скидки, ₽ | B8: 136195 | C8: 175920 | D8: 301753 | E8: 201196 | F8: 345195 | G8: 365857 | H8: 170476 | I8: 78017
A9: Скидки, % от услуг | B9: =B8/B3 | C9: =C8/C3 | D9: =D8/D3 | E9: =E8/E3 | F9: =F8/F3 | G9: =G8/G3 | H9: =H8/H3 | I9: =I8/I3
A10: Потерянные клиенты (>90 дней) | B10: 484 | C10: 518 | D10: 539 | E10: 537 | F10: 565 | G10: 618 | H10: 683 | I10: 729
A12: Август — партиал месяц (данные по 21.08).

Sheet Прогноз выручки
A1: Прогноз выручки сен-дек 2026 — driver-based, меняй допущения на первом листе
A3: Сценарий | B3: Сентябрь | C3: Октябрь | D3: Ноябрь | E3: Декабрь | F3: Итого 4 мес
A4: Пессимистичный | B4: =Допущения!$B$4*(1+Допущения!$B$7) | C4: =Допущения!$B$4*(1+Допущения!$B$7) | D4: =Допущения!$B$4*(1+Допущения!$B$7) | E4: =Допущения!$B$4*(1+Допущения!$B$7) | F4: =SUM(B4:E4)
A5: Базовый | B5: =Допущения!$B$4*(1+Допущения!$B$5) | C5: =Допущения!$B$4*(1+Допущения!$B$5) | D5: =Допущения!$B$4*(1+Допущения!$B$5) | E5: =Допущения!$B$4*(1+Допущения!$B$5) | F5: =SUM(B5:E5)
A6: Оптимистичный | B6: =Допущения!$B$4*(1+Допущения!$B$6) | C6: =Допущения!$B$4*(1+Допущения!$B$6) | D6: =Допущения!$B$4*(1+Допущения!$B$6) | E6: =Допущения!$B$4*(1+Допущения!$B$6) | F6: =SUM(B6:E6)
A9: Логика: одна и та же база (среднее июнь-июль) применяется ко всем 4 месяцам, без сезонности внутри периода — если знаешь сезонные пики/спады (отпуска, праздники), скажи, добавлю коэффициенты по месяцам.

Sheet Прогноз прибыли
A1: Прогноз расходов и чистой прибыли сен-дек 2026 (Базовый сценарий)
A3: Статья | B3: Сентябрь | C3: Октябрь | D3: Ноябрь | E3: Декабрь | F3: Итого 4 мес
A4: Выручка (базовый сценарий) | B4: ='Прогноз выручки'!B5 | C4: ='Прогноз выручки'!C5 | D4: ='Прогноз выручки'!D5 | E4: ='Прогноз выручки'!E5 | F4: =SUM(B4:E4)
A5: Переменные расходы | B5: =-B4*Допущения!$B$8 | C5: =-C4*Допущения!$B$8 | D5: =-D4*Допущения!$B$8 | E5: =-E4*Допущения!$B$8 | F5: =SUM(B5:E5)
A6: Постоянные расходы | B6: =-Допущения!$B$9 | C6: =-Допущения!$B$9 | D6: =-Допущения!$B$9 | E6: =-Допущения!$B$9 | F6: =SUM(B6:E6)
A7: Закупка косметики (сглажено) | B7: =-Допущения!$B$10 | C7: =-Допущения!$B$10 | D7: =-Допущения!$B$10 | E7: =-Допущения!$B$10 | F7: =SUM(B7:E7)
A8: Чистая прибыль (прогноз) | B8: =SUM(B4:B7) | C8: =SUM(C4:C7) | D8: =SUM(D4:D7) | E8: =SUM(E4:E7) | F8: =SUM(B8:E8)
A10: Рентабельность по чистой прибыли, % | B10: =B8/B4 | C10: =C8/C4 | D10: =D8/D4 | E10: =E8/E4 | F10: =F8/F4

Sheet Косметика — методология
A1: Закупка косметики на продажу — открытый методологический вопрос
A3: Проблема | B3: Сейчас в П&Л закупка списывается целиком в месяц оплаты поставщику, но это запас на несколько месяцев продаж вперёд — из-за этого П&Л скачет (март/июнь/июль искажены разовыми крупными закупками).
A5: Что я сделала для модели | B5: Взяла ИТОГО закупок янв-авг (1 075 507 ₽) / 8 месяцев = 134 438 ₽/мес как сглаженную оценку — это ВРЕМЕННОЕ решение для прогноза, не бухгалтерская правильная амортизация.
A7: Как сделать правильно | B7: Нужно знать остатки товара на складе на конец каждого месяца (у меня есть текущий снимок остатков в дашборде ЭЛАМИ, но не исторический по месяцам) — тогда можно считать реальный расход = закупки + начальный остаток − конечный остаток, а не по факту оплаты поставщику.
A9: Что нужно от тебя | B9: Скажи: (а) устраивает ли сглаживание по среднему как временное решение, (б) можно ли начать фиксировать остатки на конец каждого месяца, чтобы перейти на правильный метод.
